<?xml version="1.0" encoding="utf-8"?>
<TestPaper CateId="5196" QuestionNum="25" SingleNum="8" MultiNum="1" PanDunNum="16">
  <Single>
    <QuestionInfo1 id="140006">
      <Question>对于我们经销商来说，为了应对三包政策，我们应在库存管理维护上有相应措施，应保持合理库存，同时关注长库存车，尽量避免库存车停放超过（）。</Question>
      <A>9个月</A>
      <B>3个月</B>
      <C>1年</C>
      <D>6个月</D>
      <Answer>D</Answer>
      <CustomerAnswer>A</CustomerAnswer>
      <Style>1</Style>
      <CompanyId>0</CompanyId>
      <QuestionId>140006</QuestionId>
    </QuestionInfo1>
    <QuestionInfo2 id="140004">
      <Question>销售车辆在发放三包凭证时，经销商在填写并盖章之后，在交付客户之前，需将凭证进行复印。复印件由经销商保存至少（），以备国家相关部门核查。</Question>
      <A>10年以上</A>
      <B>8年以上</B>
      <C>3年以上</C>
      <D>5年以上</D>
      <Answer>D</Answer>
      <CustomerAnswer>A</CustomerAnswer>
      <Style>1</Style>
      <CompanyId>0</CompanyId>
      <QuestionId>140004</QuestionId>
    </QuestionInfo2>
    <QuestionInfo3 id="139997">
      <Question>三包有效期内，消费者书面要求更换、退货的，经销商应当自消费者要求更换、退货之日起（）内，作出书面答复。</Question>
      <A>15个工作日</A>
      <B>10个工作日</B>
      <C>5个工作日</C>
      <D>7个工作日</D>
      <Answer>B</Answer>
      <CustomerAnswer>A</CustomerAnswer>
      <Style>1</Style>
      <CompanyId>0</CompanyId>
      <QuestionId>139997</QuestionId>
    </QuestionInfo3>
    <QuestionInfo4 id="139998">
      <Question>三包政策指出在包修期内，因质量问题每次修理时间（包括等待修理备用件时间）超过（）的：经销商应当为消费者提供备用车或者给予合理的交通费用补偿。</Question>
      <A>5日</A>
      <B>10日</B>
      <C>3日</C>
      <D>7日</D>
      <Answer>A</Answer>
      <CustomerAnswer>A</CustomerAnswer>
      <Style>1</Style>
      <CompanyId>0</CompanyId>
      <QuestionId>139998</QuestionId>
    </QuestionInfo4>
    <QuestionInfo5 id="139996">
      <Question>在三包期内，按规定更换或者退货的，消费者应当支付因使用家用汽车产品所产生的合理使用补偿，经销商依照本规定应当免费更换、退货的除外(60天/3000公里)。合理使用补偿费用的计算公式为： [（车价款（元）×行驶里程（km））/1000]×（）。</Question>
      <A>0.02</A>
      <B>0.005</B>
      <C>0.008</C>
      <D>0.01</D>
      <Answer>C</Answer>
      <CustomerAnswer>A</CustomerAnswer>
      <Style>1</Style>
      <CompanyId>0</CompanyId>
      <QuestionId>139996</QuestionId>
    </QuestionInfo5>
    <QuestionInfo6 id="139999">
      <Question>在三包期内，易损耗零部件在其明示的质量保质期内出现产品质量问题的可以免费更换零部件，并且易损耗件还会计入维修时间和次数，如以下（）情况。</Question>
      <A>其他选项都正确</A>
      <B>在损耗件质量保证期外，因损耗件质量问题而导致的更换或维修</B>
      <C>因损耗件的正常磨损、消耗而导致的保养、维修</C>
      <D>在损耗件质量保证期内，因损耗件质量问题而导致的更换或维修</D>
      <Answer>D</Answer>
      <CustomerAnswer>
      </CustomerAnswer>
      <Style>1</Style>
      <CompanyId>0</CompanyId>
      <QuestionId>139999</QuestionId>
    </QuestionInfo6>
    <QuestionInfo7 id="139995">
      <Question>（）是指“产品质量等同或者高于装车零部件标准要求，且具有良好装车性能的配件”。除4S店外，非4S店也需要提供“（）”，并要逐步对车辆维修记录进行统一存档管理，将一辆车的所有维修保养记录电子化并全行业可查。</Question>
      <A>副厂配件</A>
      <B>同质配件</B>
      <C>高仿配件</C>
      <D>原装配件</D>
      <Answer>B</Answer>
      <CustomerAnswer>
      </CustomerAnswer>
      <Style>1</Style>
      <CompanyId>0</CompanyId>
      <QuestionId>139995</QuestionId>
    </QuestionInfo7>
    <QuestionInfo8 id="140005">
      <Question>作为经销商，我们希望店内的（）负责对销售流程中的有关三包的应对和话术进行考核与监督，通过管理手段切实保障客户利益。</Question>
      <A>销售顾问</A>
      <B>市场经理</B>
      <C>销售经理</C>
      <D>内训师</D>
      <Answer>C</Answer>
      <CustomerAnswer>
      </CustomerAnswer>
      <Style>1</Style>
      <CompanyId>0</CompanyId>
      <QuestionId>140005</QuestionId>
    </QuestionInfo8>
  </Single>
  <Multi>
    <QuestionInfo1 id="140008">
      <Question>符合“三包”规定的车辆一旦出现以下情况（）就可进行免费更换、退货。</Question>
      <A>严重安全性能故障累计修理2次未排除</A>
      <B>60日/3000公里期间内转向系统、制动系统失效</B>
      <C>60日/3000公里期间内车身开裂</C>
      <D>60日/3000公里期间内燃油泄漏</D>
      <Answer>BCD</Answer>
      <CustomerAnswer>
      </CustomerAnswer>
      <Style>2</Style>
      <CompanyId>0</CompanyId>
      <QuestionId>140008</QuestionId>
    </QuestionInfo1>
  </Multi>
  <PanDuan>
    <QuestionInfo1 id="140021">
      <Question>2016.1.1号起“原厂配件”不再“横行霸道”，车主可以自己购买一个质量、配置差不多的零配件进行更换，4S店或厂家不能以此为借口推卸责任。其实剥夺原厂配件的“专制权”，提倡同质配件的流通，对第三方汽车维修机构是一个发展机会，普通消费者也将获得更实惠的售后服务价格，一举多得！</Question>
      <A>
      </A>
      <B>
      </B>
      <C>
      </C>
      <D>
      </D>
      <Answer>1</Answer>
      <CustomerAnswer>
      </CustomerAnswer>
      <Style>3</Style>
      <CompanyId>0</CompanyId>
      <QuestionId>140021</QuestionId>
    </QuestionInfo1>
    <QuestionInfo2 id="140029">
      <Question>对于客户购车信息情况（从开票之日起进行计算），销售顾问应严格执行三包政策，准确无误地上报，~可以酌情进行晚报，但绝不能进行虚报~。</Question>
      <A>不得出现将客户购车情况进行晚报、虚报等</A>
      <B>
      </B>
      <C>
      </C>
      <D>
      </D>
      <Answer>0</Answer>
      <CustomerAnswer>
      </CustomerAnswer>
      <Style>3</Style>
      <CompanyId>0</CompanyId>
      <QuestionId>140029</QuestionId>
    </QuestionInfo2>
    <QuestionInfo3 id="140024">
      <Question>国家税务总局发布的《车船税管理规定（试行）》规定：已缴纳车船税的车船，因质量原因，车船被退回生产企业或者经销商的，纳税人可以向纳税所在地的主管税务机关申请退还自退货月份起至纳税年度终了期间的税款，退货月份以退货发票所载日期的当月为准。</Question>
      <A>
      </A>
      <B>
      </B>
      <C>
      </C>
      <D>
      </D>
      <Answer>1</Answer>
      <CustomerAnswer>
      </CustomerAnswer>
      <Style>3</Style>
      <CompanyId>0</CompanyId>
      <QuestionId>140024</QuestionId>
    </QuestionInfo3>
    <QuestionInfo4 id="140026">
      <Question>销售顾问在进行产品介绍、客户商谈过程中，应明确向客户表明：我品牌所生产销售的进口车辆，是满足“三包”质量监控要求的！而对于三包中的负面信息，销售顾问~可以适当向客户隐瞒~。</Question>
      <A>不得为了盈利而有意向客户隐瞒</A>
      <B>
      </B>
      <C>
      </C>
      <D>
      </D>
      <Answer>0</Answer>
      <CustomerAnswer>
      </CustomerAnswer>
      <Style>3</Style>
      <CompanyId>0</CompanyId>
      <QuestionId>140026</QuestionId>
    </QuestionInfo4>
    <QuestionInfo5 id="140025">
      <Question>新修订的电动汽车充电接口及通信协议5项国家标准正式实施，要求提高电动汽车充电设施安全性及兼容性。交流充电和直流充电都有更严格的充电规范要求。</Question>
      <A>
      </A>
      <B>
      </B>
      <C>
      </C>
      <D>
      </D>
      <Answer>1</Answer>
      <CustomerAnswer>
      </CustomerAnswer>
      <Style>3</Style>
      <CompanyId>0</CompanyId>
      <QuestionId>140025</QuestionId>
    </QuestionInfo5>
    <QuestionInfo6 id="140031">
      <Question>对于跨地区销售的客户，如果符合三包范围，需要维修或更换，可以执行；但如果需要退车，应不予以受理，告知客户必须去当时购买的经销商店进行退车申请。</Question>
      <A>
      </A>
      <B>
      </B>
      <C>
      </C>
      <D>
      </D>
      <Answer>1</Answer>
      <CustomerAnswer>
      </CustomerAnswer>
      <Style>3</Style>
      <CompanyId>0</CompanyId>
      <QuestionId>140031</QuestionId>
    </QuestionInfo6>
    <QuestionInfo7 id="140018">
      <Question>如消费者遗失三包凭证，经销商、生产者应当积极协助办理，并在接到消费者申请后10个工作日内予以补办。补办三包凭证后，可以依照本规定继续享有相应权利。</Question>
      <A>
      </A>
      <B>
      </B>
      <C>
      </C>
      <D>
      </D>
      <Answer>1</Answer>
      <CustomerAnswer>
      </CustomerAnswer>
      <Style>3</Style>
      <CompanyId>0</CompanyId>
      <QuestionId>140018</QuestionId>
    </QuestionInfo7>
    <QuestionInfo8 id="140023">
      <Question>汽车零部件的统一编码与标识、国家标准将正式实施。标准规定了汽车零部件统一编码的编码原则、数据结构，符号表示方法及其位置的一般原则。适用于汽车零部件(配件)统一编码和标识的编制，以及汽车零部件(配件)的信息采集及数据交换。</Question>
      <A>
      </A>
      <B>
      </B>
      <C>
      </C>
      <D>
      </D>
      <Answer>1</Answer>
      <CustomerAnswer>
      </CustomerAnswer>
      <Style>3</Style>
      <CompanyId>0</CompanyId>
      <QuestionId>140023</QuestionId>
    </QuestionInfo8>
    <QuestionInfo9 id="140011">
      <Question>消费者在三包有效期内，符合本规定更换、退货条件的，~仅凭购车发票~就可以由经销商处进行更换、退货。</Question>
      <A>三包凭证、购车发票</A>
      <B>
      </B>
      <C>
      </C>
      <D>
      </D>
      <Answer>0</Answer>
      <CustomerAnswer>
      </CustomerAnswer>
      <Style>3</Style>
      <CompanyId>0</CompanyId>
      <QuestionId>140011</QuestionId>
    </QuestionInfo9>
    <QuestionInfo10 id="140017">
      <Question>按规定更换、退货的家用汽车产品经维修检验合格的，再次销售时，销售商应当明示该车是“三包换退车”，并注明更换、退货的原因。</Question>
      <A>
      </A>
      <B>
      </B>
      <C>
      </C>
      <D>
      </D>
      <Answer>1</Answer>
      <CustomerAnswer>
      </CustomerAnswer>
      <Style>3</Style>
      <CompanyId>0</CompanyId>
      <QuestionId>140017</QuestionId>
    </QuestionInfo10>
    <QuestionInfo11 id="140016">
      <Question>三包政策指出经销商应当自消费者要求退货之日起~10~个工作日内向消费者出具退车证明，并负责为消费者按发票价格一次退清货款。</Question>
      <A>15</A>
      <B>
      </B>
      <C>
      </C>
      <D>
      </D>
      <Answer>0</Answer>
      <CustomerAnswer>
      </CustomerAnswer>
      <Style>3</Style>
      <CompanyId>0</CompanyId>
      <QuestionId>140016</QuestionId>
    </QuestionInfo11>
    <QuestionInfo12 id="140027">
      <Question>销售顾问在客户付款后，根据《购销合同》，将客户信息、经销商信息填入《三包凭证》。交车时，销售顾问应向客户转交所有随车文件，解释文件内容和用途，包括《三包凭证》和新版《质量担保条例》的使用规范、注意事项等，最后将三包信息录入相关系统中。</Question>
      <A>
      </A>
      <B>
      </B>
      <C>
      </C>
      <D>
      </D>
      <Answer>1</Answer>
      <CustomerAnswer>
      </CustomerAnswer>
      <Style>3</Style>
      <CompanyId>0</CompanyId>
      <QuestionId>140027</QuestionId>
    </QuestionInfo12>
    <QuestionInfo13 id="140033">
      <Question>~生产商~作为有关三包政策的标准执行者、服务水平的缔造者，不要向客户做过度承诺，应做到专业解读、准确传递！</Question>
      <A>经销商</A>
      <B>
      </B>
      <C>
      </C>
      <D>
      </D>
      <Answer>0</Answer>
      <CustomerAnswer>
      </CustomerAnswer>
      <Style>3</Style>
      <CompanyId>0</CompanyId>
      <QuestionId>140033</QuestionId>
    </QuestionInfo13>
    <QuestionInfo14 id="140019">
      <Question>在家用汽车产品包修期和三包有效期内发生家用汽车产品所有权转移的，~三包凭证不会随车转移，新车主需要重新向商家申请三包证~，同时三包责任不因汽车所有权转移而改变。</Question>
      <A>三包凭证应当随车转移</A>
      <B>
      </B>
      <C>
      </C>
      <D>
      </D>
      <Answer>0</Answer>
      <CustomerAnswer>
      </CustomerAnswer>
      <Style>3</Style>
      <CompanyId>0</CompanyId>
      <QuestionId>140019</QuestionId>
    </QuestionInfo14>
    <QuestionInfo15 id="140034">
      <Question>为了应对三包政策，每家4S店的总经理应从高级管理者的角度协调售前和售后等多个岗位，保证对PDI检查的执行与记录，同时保持对长库存车的关注，采取恰当的应对策略。</Question>
      <A>
      </A>
      <B>
      </B>
      <C>
      </C>
      <D>
      </D>
      <Answer>1</Answer>
      <CustomerAnswer>
      </CustomerAnswer>
      <Style>3</Style>
      <CompanyId>0</CompanyId>
      <QuestionId>140034</QuestionId>
    </QuestionInfo15>
    <QuestionInfo16 id="140010">
      <Question>三包主张谁~生产~谁负责，因为~销售者~与消费者之间无直接法律关系的，而~生产者~是直接与消费者订立买卖合同的当事人，所以“三包”责任主体是~生产者~。</Question>
      <A>销售~生产者~销售者~销售者</A>
      <B>
      </B>
      <C>
      </C>
      <D>
      </D>
      <Answer>0</Answer>
      <CustomerAnswer>
      </CustomerAnswer>
      <Style>3</Style>
      <CompanyId>0</CompanyId>
      <QuestionId>140010</QuestionId>
    </QuestionInfo16>
  </PanDuan>
</TestPaper>